aprsd_locationdata_plugin/__init__.py
aprsd_locationdata_plugin/aprsd_locationdata_plugin.py
aprsd_locationdata_plugin/conf/__init__.py
aprsd_locationdata_plugin/conf/main.py
aprsd_locationdata_plugin/conf/opts.py
aprsd_locationdata_plugin-0.3.0.dist-info/LICENSE
aprsd_locationdata_plugin-0.3.0.dist-info/METADATA
aprsd_locationdata_plugin-0.3.0.dist-info/WHEEL
aprsd_locationdata_plugin-0.3.0.dist-info/entry_points.txt
aprsd_locationdata_plugin-0.3.0.dist-info/pbr.json
aprsd_locationdata_plugin-0.3.0.dist-info/top_level.txt
aprsd_locationdata_plugin-0.3.0.dist-info/RECORD
